CHANGELOG.md
MANIFEST.in
README.rst
setup.py
pythong/__init__.py
pythong/classifiers.py
pythong/command.py
pythong/project.py
pythong/util.py
pythong/version.py
pythong.egg-info/PKG-INFO
pythong.egg-info/SOURCES.txt
pythong.egg-info/dependency_links.txt
pythong.egg-info/entry_points.txt
pythong.egg-info/not-zip-safe
pythong.egg-info/requires.txt
pythong.egg-info/top_level.txt
pythong/templates/distribute_setup.py.jinja
pythong/templates/setup.py.jinja