Metadata-Version: 1.1
Name: pythong
Version: 0.6.6
Summary: Set up a minimal, yet comfortable structure                     for a Python project
Home-page: http://github.com/oddshocks/pythong
Author: David Gay
Author-email: oddshocks@riseup.net
License: GPLv3+
Keywords: python development project bootstrap
Platform: UNKNOWN
Classifier: Development Status :: 2 - Pre-Alpha
Classifier: Intended Audience :: Developers
Classifier: License :: OSI Approved :: GNU General Public License (GPL)
Classifier: Programming Language :: Python :: 2
Classifier: Topic :: Software Development
Classifier: Topic :: Utilities
